Basic_Maths/__init__.py
Basic_Maths/lib_ver_info.py
Basic_Maths/library_func.py
Basic_Maths/Lib/lib.py
Basic_Maths/Lib/parameters.py
lxlm_basic_maths-6.5.dist-info/licenses/LICENSE
lxlm_basic_maths-6.5.dist-info/METADATA
lxlm_basic_maths-6.5.dist-info/WHEEL
lxlm_basic_maths-6.5.dist-info/top_level.txt
lxlm_basic_maths-6.5.dist-info/RECORD
