Metadata-Version: 2.4
Name: LXLM-Basic_Maths
Version: 6.5
Summary: Basic_Maths is a lightweight, minimal, and easy-to-use Python library designed for performing basic mathematical operations quickly and simply, without unnecessary complexity.
Author: LinuxUsersLinuxMint
License:                     GNU GENERAL PUBLIC LICENSE
Project-URL: Homepage, https://github.com/LinuxUsersLinuxMint/Basic_Maths
Project-URL: Source, https://github.com/LinuxUsersLinuxMint/Basic_Maths
Requires-Python: >=3.7
License-File: LICENSE
Requires-Dist: pyappdevkit>=2.2
Dynamic: license-file
